LnkParse3/__init__.py
LnkParse3/decorators.py
LnkParse3/exceptions.py
LnkParse3/extra_data.py
LnkParse3/extra_factory.py
LnkParse3/info_factory.py
LnkParse3/lnk_file.py
LnkParse3/lnk_header.py
LnkParse3/lnk_info.py
LnkParse3/lnk_targets.py
LnkParse3/string_data.py
LnkParse3/target_factory.py
LnkParse3/text_processor.py
LnkParse3/utils.py
LnkParse3/extra/__init__.py
LnkParse3/extra/code_page.py
LnkParse3/extra/console.py
LnkParse3/extra/darwin.py
LnkParse3/extra/distributed_tracker.py
LnkParse3/extra/environment.py
LnkParse3/extra/icon.py
LnkParse3/extra/known_folder.py
LnkParse3/extra/lnk_extra_base.py
LnkParse3/extra/metadata.py
LnkParse3/extra/shell_item.py
LnkParse3/extra/shim_layer.py
LnkParse3/extra/special_folder.py
LnkParse3/extra/terminal.py
LnkParse3/extra/unknown.py
LnkParse3/info/__init__.py
LnkParse3/info/local.py
LnkParse3/info/network.py
LnkParse3/target/__init__.py
LnkParse3/target/common_places_folder.py
LnkParse3/target/compressed_folder.py
LnkParse3/target/control_panel.py
LnkParse3/target/internet.py
LnkParse3/target/lnk_target_base.py
LnkParse3/target/my_computer.py
LnkParse3/target/network_location.py
LnkParse3/target/printers.py
LnkParse3/target/root_folder.py
LnkParse3/target/shell_fs_folder.py
LnkParse3/target/unknown.py
LnkParse3/target/users_files_folder.py
lnkparse3-1.5.3.dist-info/licenses/LICENSE
lnkparse3-1.5.3.dist-info/METADATA
lnkparse3-1.5.3.dist-info/WHEEL
lnkparse3-1.5.3.dist-info/entry_points.txt
lnkparse3-1.5.3.dist-info/top_level.txt
lnkparse3-1.5.3.dist-info/RECORD
