Metadata-Version: 2.4
Name: LnkParse3
Version: 1.5.3
Summary: Windows Shortcut file (LNK) parser
Home-page: https://github.com/Matmaus/LnkParse
Author: Matmaus
Author-email: matusjas.work@gmail.com
License: MIT
Classifier: Programming Language :: Python :: 3
Classifier: License :: OSI Approved :: MIT License
Classifier: Operating System :: OS Independent
License-File: LICENSE
Requires-Dist: pyyaml
Dynamic: author
Dynamic: author-email
Dynamic: classifier
Dynamic: description
Dynamic: description-content-type
Dynamic: home-page
Dynamic: license
Dynamic: license-file
Dynamic: requires-dist
Dynamic: summary
